{
  "120363419059621769@g.us": {
    "isBanned": false,
    "welcome": false,
    "antiLink": false,
    "delete": true,
    "expired": null
  },
  "120363335769427344@g.us": {
    "isBanned": false,
    "welcome": false,
    "antiLink": false,
    "delete": true,
    "expired": null
  },
  "120363162588006144@g.us": {
    "isBanned": false,
    "welcome": false,
    "antiLink": false,
    "delete": true,
    "expired": null
  },
  "120363385204085212@g.us": {
    "isBanned": false,
    "welcome": false,
    "antiLink": false,
    "delete": true,
    "expired": null
  },
  "120363402417291351@g.us": {
    "isBanned": false,
    "welcome": false,
    "antiLink": false,
    "delete": true,
    "expired": null
  },
  "120363404178043051@g.us": {
    "isBanned": false,
    "welcome": false,
    "antiLink": false,
    "delete": true,
    "expired": null
  },
  "120363418085266803@g.us": {
    "isBanned": false,
    "welcome": false,
    "antiLink": false,
    "delete": true,
    "expired": null
  },
  "120363402770234934@g.us": {
    "isBanned": false,
    "welcome": false,
    "antiLink": false,
    "delete": true,
    "expired": null
  },
  "120363399356821789@g.us": {
    "isBanned": false,
    "welcome": false,
    "antiLink": false,
    "delete": true,
    "expired": null
  },
  "120363400692510989@g.us": {
    "isBanned": false,
    "welcome": false,
    "antiLink": false,
    "delete": true,
    "expired": null
  },
  "120363401216188498@g.us": {
    "isBanned": false,
    "welcome": false,
    "antiLink": false,
    "delete": true,
    "expired": null
  },
  "120363404894058220@g.us": {
    "isBanned": false,
    "welcome": false,
    "antiLink": false,
    "delete": true,
    "expired": null
  },
  "120363378532473151@g.us": {
    "isBanned": false,
    "welcome": false,
    "antiLink": false,
    "delete": true,
    "expired": null
  },
  "120363418540595233@g.us": {
    "isBanned": false,
    "welcome": false,
    "antiLink": false,
    "delete": true,
    "expired": null
  },
  "120363399996195320@g.us": {
    "isBanned": false,
    "welcome": false,
    "antiLink": false,
    "delete": true,
    "expired": null
  },
  "120363419837509568@g.us": {
    "isBanned": false,
    "welcome": false,
    "antiLink": false,
    "delete": true,
    "expired": null
  },
  "120363417832007908@g.us": {
    "isBanned": false,
    "welcome": false,
    "antiLink": false,
    "delete": true,
    "expired": null
  },
  "120363418675672292@g.us": {
    "isBanned": false,
    "welcome": false,
    "antiLink": false,
    "delete": true,
    "expired": null
  },
  "120363419022074878@g.us": {
    "isBanned": false,
    "welcome": false,
    "antiLink": false,
    "delete": true,
    "expired": null
  },
  "120363391062591688@g.us": {
    "isBanned": false,
    "welcome": false,
    "antiLink": false,
    "delete": true,
    "expired": null
  },
  "120363419020371134@g.us": {
    "isBanned": false,
    "welcome": false,
    "antiLink": false,
    "delete": true,
    "expired": null
  },
  "120363418780280063@g.us": {
    "isBanned": false,
    "welcome": false,
    "antiLink": false,
    "delete": true,
    "expired": null
  },
  "120363372051382245@g.us": {
    "isBanned": false,
    "welcome": false,
    "antiLink": false,
    "delete": true,
    "expired": null
  },
  "120363404192256370@g.us": {
    "isBanned": false,
    "welcome": false,
    "antiLink": false,
    "delete": true,
    "expired": null
  },
  "120363384799122111@g.us": {
    "isBanned": false,
    "welcome": false,
    "antiLink": false,
    "delete": true,
    "expired": null
  },
  "120363414177770034@g.us": {
    "isBanned": false,
    "welcome": false,
    "antiLink": false,
    "delete": true,
    "expired": null
  },
  "120363413504336578@g.us": {
    "isBanned": false,
    "welcome": false,
    "antiLink": false,
    "delete": true,
    "expired": null
  },
  "120363321406645576@g.us": {
    "isBanned": false,
    "welcome": false,
    "antiLink": false,
    "delete": true,
    "expired": null
  },
  "120363373031297929@g.us": {
    "isBanned": false,
    "welcome": false,
    "antiLink": false,
    "delete": true,
    "expired": null
  },
  "120363167090327239@g.us": {
    "isBanned": false,
    "welcome": false,
    "antiLink": false,
    "delete": true,
    "expired": null
  },
  "120363402819835749@g.us": {
    "isBanned": false,
    "welcome": false,
    "antiLink": false,
    "delete": true,
    "expired": null
  },
  "120363316378962022@g.us": {
    "isBanned": false,
    "welcome": false,
    "antiLink": false,
    "delete": true,
    "expired": null
  },
  "120363224100277097@g.us": {
    "isBanned": false,
    "welcome": false,
    "antiLink": false,
    "delete": true,
    "expired": null
  },
  "120363418351640194@g.us": {
    "isBanned": false,
    "welcome": false,
    "antiLink": false,
    "delete": true,
    "expired": null
  }
}